agentmake/README.md
agentmake/__init__.py
agentmake/agentmake.env
agentmake/config.py
agentmake/etextedit.py
agentmake/example.bat
agentmake/main.py
agentmake/requirements.txt
agentmake/version.txt
agentmake/agents/README.md
agentmake/agents/auto_prompt_engineering.py
agentmake/agents/auto_tool_selection.py
agentmake/agents/deep_reflection.py
agentmake/agents/letmedoit.py
agentmake/agents/letmedoit_lite.py
agentmake/agents/reasoning.py
agentmake/agents/super.py
agentmake/agents/teamwork.py
agentmake/backends/anthropic.py
agentmake/backends/azure_anthropic.py
agentmake/backends/azure_cohere.py
agentmake/backends/azure_deepseek.py
agentmake/backends/azure_mistral.py
agentmake/backends/azure_openai.py
agentmake/backends/azure_sdk.py
agentmake/backends/azure_xai.py
agentmake/backends/cohere.py
agentmake/backends/custom.py
agentmake/backends/custom1.py
agentmake/backends/custom2.py
agentmake/backends/deepseek.py
agentmake/backends/genai.py
agentmake/backends/github.py
agentmake/backends/github_any.py
agentmake/backends/googleai.py
agentmake/backends/groq.py
agentmake/backends/llamacpp.py
agentmake/backends/mistral.py
agentmake/backends/ollama.py
agentmake/backends/ollamacloud.py
agentmake/backends/openai.py
agentmake/backends/xai.py
agentmake/etextedit_plugins/Analyze.py
agentmake/etextedit_plugins/British English.py
agentmake/etextedit_plugins/Custom Prompt.py
agentmake/etextedit_plugins/Elaborate.py
agentmake/etextedit_plugins/Explain.py
agentmake/etextedit_plugins/Friendly Tone.py
agentmake/etextedit_plugins/Markdown.py
agentmake/etextedit_plugins/Professional Tone.py
agentmake/etextedit_plugins/Prompt Engineering.py
agentmake/etextedit_plugins/Refine English.py
agentmake/etextedit_plugins/Speak.py
agentmake/etextedit_plugins/Summarize.py
agentmake/etextedit_plugins/Translate into.py
agentmake/instructions/README.md
agentmake/instructions/reflect.md
agentmake/instructions/simple.md
agentmake/instructions/think.md
agentmake/instructions/bible/application.md
agentmake-1.2.13.dist-info/LICENSE
agentmake-1.2.13.dist-info/METADATA
agentmake-1.2.13.dist-info/WHEEL
agentmake-1.2.13.dist-info/entry_points.txt
agentmake-1.2.13.dist-info/top_level.txt
agentmake-1.2.13.dist-info/RECORD
