Metadata-Version: 2.1
Name: agentmake
Version: 1.2.13
Summary: AgentMake AI: an agent developement kit (ADK) for developing agentic AI applications that support 16 AI backends and work with 7 agentic components, such as tools and agents. (Developer: Eliran Wong)
Home-page: https://github.com/eliranwong/agentmake
Author: Eliran Wong
Author-email: support@toolmate.ai
License: GNU General Public License (GPL)
Project-URL: Source, https://github.com/eliranwong/agentmake
Project-URL: Tracker, https://github.com/eliranwong/agentmake/issues
Project-URL: Documentation, https://github.com/eliranwong/agentmake/wiki
Project-URL: Funding, https://www.paypal.me/toolmate
Keywords: toolmate ai sdk adk anthropic azure chatgpt cohere deepseek genai github googleai groq llamacpp mistral ollama openai vertexai xai mesop
Classifier: Development Status :: 5 - Production/Stable
Classifier: Intended Audience :: End Users/Desktop
Classifier: Topic :: Utilities
Classifier: Topic :: Scientific/Engineering :: Artificial Intelligence
Classifier: Topic :: Software Development :: Build Tools
Classifier: License :: OSI Approved :: GNU General Public License v3 or later (GPLv3+)
Classifier: Programming Language :: Python :: 3.8
Classifier: Programming Language :: Python :: 3.9
Classifier: Programming Language :: Python :: 3.10
Classifier: Programming Language :: Python :: 3.11
Classifier: Programming Language :: Python :: 3.12
Requires-Python: >=3.8, <3.13
License-File: LICENSE
Requires-Dist: anthropic >=0.75.0
Requires-Dist: apsw
Requires-Dist: azure-ai-inference
Requires-Dist: beautifulsoup4
Requires-Dist: cohere >=5.16.1
Requires-Dist: edge-tts >=7.2.7
Requires-Dist: flashtext
Requires-Dist: geocoder
Requires-Dist: groq >=0.33.0
Requires-Dist: html2text
Requires-Dist: importlib-metadata
Requires-Dist: lightrag-hku
Requires-Dist: markdown
Requires-Dist: markitdown[all]
Requires-Dist: mistralai >=1.9.2
Requires-Dist: nano-vectordb
Requires-Dist: networkx
Requires-Dist: numpy ==1.26.4
Requires-Dist: ollama >=0.5.1
Requires-Dist: openai >=2.14.0
Requires-Dist: packaging
Requires-Dist: pendulum
Requires-Dist: pipmaster
Requires-Dist: prompt-toolkit
Requires-Dist: psutil
Requires-Dist: pygments
Requires-Dist: pypandoc
Requires-Dist: pyperclip
Requires-Dist: python-docx
Requires-Dist: python-dotenv
Requires-Dist: pytz
Requires-Dist: setuptools
Requires-Dist: setuptools-rust
Requires-Dist: sounddevice
Requires-Dist: soundfile
Requires-Dist: tenacity
Requires-Dist: tiktoken >=0.9.0
Requires-Dist: xonsh[full]
Provides-Extra: genai
Requires-Dist: google-genai >=1.46.0 ; extra == 'genai'
Provides-Extra: mcp
Requires-Dist: agentmakemcp >=0.0.4 ; extra == 'mcp'
Provides-Extra: studio
Requires-Dist: agentmakestudio >=0.0.10 ; extra == 'studio'
